otava/analysis.py
otava/attributes.py
otava/bigquery.py
otava/config.py
otava/csv_options.py
otava/data_selector.py
otava/grafana.py
otava/graphite.py
otava/importer.py
otava/main.py
otava/postgres.py
otava/report.py
otava/series.py
otava/slack.py
otava/test_config.py
otava/util.py
otava/resources/otava.yaml
apache_otava-0.7.0.dist-info/METADATA
apache_otava-0.7.0.dist-info/WHEEL
apache_otava-0.7.0.dist-info/entry_points.txt
apache_otava-0.7.0.dist-info/licenses/LICENSE
apache_otava-0.7.0.dist-info/licenses/NOTICE
apache_otava-0.7.0.dist-info/RECORD
