Metadata-Version: 2.4
Name: apache-otava
Version: 0.7.0
Summary: Apache Otava (Incubating): Change Detection for Continuous Performance Engineering
Project-URL: Homepage, https://otava.apache.org
Project-URL: Documentation, https://otava.apache.org/docs/overview
Project-URL: Repository, https://github.com/apache/otava
Project-URL: Bug Tracker, https://github.com/apache/otava/issues
Author-email: "Apache Otava (Incubating)" <dev@otava.apache.org>
Maintainer-email: "Apache Otava (Incubating)" <dev@otava.apache.org>
License: Apache-2.0
License-File: LICENSE
License-File: NOTICE
Classifier: License :: OSI Approved :: Apache Software License
Classifier: Programming Language :: Python :: 3.8
Classifier: Programming Language :: Python :: 3.9
Classifier: Programming Language :: Python :: 3.10
Requires-Python: <3.11,>=3.8
Requires-Dist: dateparser>=1.0.0
Requires-Dist: expandvars>=0.6.5
Requires-Dist: google-cloud-bigquery>=3.25.0
Requires-Dist: numpy==1.24.*
Requires-Dist: pg8000>=1.31.2
Requires-Dist: pystache>=0.6.0
Requires-Dist: python-dateutil>=2.8.1
Requires-Dist: requests>=2.25.1
Requires-Dist: ruamel-yaml==0.17.21
Requires-Dist: signal-processing-algorithms==1.3.5
Requires-Dist: slack-sdk>=3.4.2
Requires-Dist: tabulate>=0.8.7
Requires-Dist: validators>=0.18.2
Provides-Extra: dev
Requires-Dist: autoflake>=1.4; extra == 'dev'
Requires-Dist: flake8>=4.0.1; extra == 'dev'
Requires-Dist: isort>=5.10.1; extra == 'dev'
Requires-Dist: pre-commit==3.5.0; extra == 'dev'
Requires-Dist: pytest-benchmark>=4.0.0; extra == 'dev'
Requires-Dist: pytest>=6.2.2; extra == 'dev'
Requires-Dist: pytz==2021.1; extra == 'dev'
Requires-Dist: ruff>=0.6.9; extra == 'dev'
Requires-Dist: tox==3.25; extra == 'dev'
